[
  {
    "action": "alert",
    "protocol": "udp",
    "source_ip": "$EXTERNAL_NET",
    "source_port": "any",
    "destination_ip": "$HOME_NET",
    "destination_port": "53",
    "sid": "2101948",
    "msg": "GPL DNS zone transfer UDP",
    "rev": "8",
    "classtype": "attempted-recon",
    "content": "|00 00 FC|",
    "offset": "14",
    "reference": [
      "cve,1999-0532",
      "nessus,10595"
    ],
    "metadata": {
      "created_at": "2010_09_23",
      "cve": "CVE_1999_0532",
      "signature_severity": "Informational",
      "updated_at": "2011_06_22"
    }
  },
  {
    "action": "alert",
    "protocol": "udp",
    "source_ip": "$EXTERNAL_NET",
    "source_port": "any",
    "destination_ip": "$HOME_NET",
    "destination_port": "53",
    "sid": "2100252",
    "msg": "GPL DNS named iquery attempt",
    "rev": "9",
    "classtype": "attempted-recon",
    "content": "|09 80 00 00 00 01 00 00 00 00|",
    "depth": "16",
    "offset": "2",
    "reference": [
      "bugtraq,134",
      "cve,1999-0009",
      "url,www.rfc-editor.org/rfc/rfc1035.txt"
    ],
    "metadata": {
      "confidence": "Medium",
      "created_at": "2010_09_23",
      "cve": "CVE_1999_0009",
      "signature_severity": "Informational",
      "updated_at": "2011_06_22"
    }
  },
  {
    "action": "alert",
    "protocol": "udp",
    "source_ip": "any",
    "source_port": "53",
    "destination_ip": "$HOME_NET",
    "destination_port": "any",
    "sid": "2016591",
    "msg": "ET DNS Reply Sinkhole - 106.187.96.49 blacklistthisdomain.com",
    "rev": "6",
    "classtype": "trojan-activity",
    "content": "|00 01 00 01|",
    "metadata": {
      "confidence": "High",
      "created_at": "2013_03_19",
      "reviewed_at": "2024_03_25",
      "signature_severity": "Major",
      "updated_at": "2014_08_26"
    }
  },
  {
    "action": "alert",
    "protocol": "udp",
    "source_ip": "any",
    "source_port": "53",
    "destination_ip": "$DNS_SERVERS",
    "destination_port": "any",
    "sid": "2013894",
    "msg": "ET DNS Excessive DNS Responses with 1 or more RR's (100+ in 10 seconds) to google.com.br possible Cache Poisoning Attempt",
    "rev": "5",
    "classtype": "bad-unknown",
    "content": "|06|google|03|com|02|br|00|",
    "reference": [
      "url,www.securelist.com/en/blog/208193214/Massive_DNS_poisoning_attacks_in_Brazil",
      "url,www.zdnet.com/blog/security/massive-dns-poisoning-attack-in-brazil-serving-exploits-and-malware/9780"
    ],
    "metadata": {
      "created_at": "2011_11_10",
      "signature_severity": "Informational",
      "updated_at": "2014_09_15"
    }
  },
  {
    "action": "alert",
    "protocol": "udp",
    "source_ip": "any",
    "source_port": "53",
    "destination_ip": "$HOME_NET",
    "destination_port": "any",
    "sid": "2016413",
    "msg": "ET DNS Reply Sinkhole - sinkhole.cert.pl 148.81.111.111",
    "rev": "5",
    "classtype": "trojan-activity",
    "content": "|00 01 00 01|",
    "metadata": {
      "confidence": "High",
      "created_at": "2013_02_15",
      "signature_severity": "Major",
      "updated_at": "2022_07_13"
    }
  },
  {
    "action": "alert",
    "protocol": "udp",
    "source_ip": "any",
    "source_port": "53",
    "destination_ip": "$HOME_NET",
    "destination_port": "any",
    "sid": "2016418",
    "msg": "ET DNS Reply Sinkhole - Dr. Web",
    "rev": "6",
    "classtype": "trojan-activity",
    "content": "|00 01 00 01|",
    "reference": [
      "url,virustracker.info"
    ],
    "metadata": {
      "confidence": "High",
      "created_at": "2013_02_16",
      "signature_severity": "Major",
      "updated_at": "2022_07_13"
    }
  },
  {
    "action": "alert",
    "protocol": "udp",
    "source_ip": "any",
    "source_port": "53",
    "destination_ip": "$HOME_NET",
    "destination_port": "any",
    "sid": "2016419",
    "msg": "ET DNS Reply Sinkhole - Zinkhole.org",
    "rev": "6",
    "classtype": "trojan-activity",
    "content": "|00 01 00 01|",
    "metadata": {
      "confidence": "High",
      "created_at": "2013_02_16",
      "signature_severity": "Major",
      "updated_at": "2022_07_13"
    }
  },
  {
    "action": "alert",
    "protocol": "udp",
    "source_ip": "any",
    "source_port": "53",
    "destination_ip": "$HOME_NET",
    "destination_port": "any",
    "sid": "2016422",
    "msg": "ET DNS Reply Sinkhole - Georgia Tech (1)",
    "rev": "6",
    "classtype": "trojan-activity",
    "content": "|00 01 00 01|",
    "reference": [
      "url,virustracker.info"
    ],
    "metadata": {
      "confidence": "High",
      "created_at": "2013_02_16",
      "signature_severity": "Major",
      "updated_at": "2022_07_13"
    }
  },
  {
    "action": "alert",
    "protocol": "udp",
    "source_ip": "any",
    "source_port": "53",
    "destination_ip": "$HOME_NET",
    "destination_port": "any",
    "sid": "2016423",
    "msg": "ET DNS Reply Sinkhole - Georgia Tech (2)",
    "rev": "7",
    "classtype": "trojan-activity",
    "content": "|00 01 00 01|",
    "reference": [
      "url,virustracker.info"
    ],
    "metadata": {
      "confidence": "High",
      "created_at": "2013_02_16",
      "signature_severity": "Major",
      "updated_at": "2022_07_13"
    }
  },
  {
    "action": "alert",
    "protocol": "udp",
    "source_ip": "$HOME_NET",
    "source_port": "any",
    "destination_ip": "any",
    "destination_port": "53",
    "sid": "2012901",
    "msg": "ET DNS Query for a Suspicious *.noc.su domain",
    "rev": "4",
    "classtype": "bad-unknown",
    "content": "|01|",
    "depth": "1",
    "offset": "2",
    "metadata": {
      "confidence": "High",
      "created_at": "2011_05_31",
      "signature_severity": "Informational",
      "updated_at": "2024_01_29"
    }
  },
  {
    "action": "alert",
    "protocol": "udp",
    "source_ip": "$HOME_NET",
    "source_port": "any",
    "destination_ip": "any",
    "destination_port": "53",
    "sid": "2013016",
    "msg": "ET DNS DNS Query for Illegal Drug Sales Site (SilkRoad)",
    "rev": "3",
    "classtype": "policy-violation",
    "content": "|01|",
    "depth": "1",
    "offset": "2",
    "metadata": {
      "confidence": "Medium",
      "created_at": "2011_06_13",
      "signature_severity": "Unknown",
      "updated_at": "2024_01_29"
    }
  },
  {
    "action": "alert",
    "protocol": "udp",
    "source_ip": "$HOME_NET",
    "source_port": "any",
    "destination_ip": "any",
    "destination_port": "53",
    "sid": "2012956",
    "msg": "ET DNS DNS Query for a Suspicious *.co.tv domain",
    "rev": "4",
    "classtype": "bad-unknown",
    "content": "|01|",
    "depth": "1",
    "offset": "2",
    "metadata": {
      "confidence": "Medium",
      "created_at": "2011_06_08",
      "signature_severity": "Informational",
      "updated_at": "2024_01_29"
    }
  },
  {
    "action": "alert",
    "protocol": "udp",
    "source_ip": "$HOME_NET",
    "source_port": "any",
    "destination_ip": "any",
    "destination_port": "53",
    "sid": "2012900",
    "msg": "ET DNS DNS Query for a Suspicious *.ae.am domain",
    "rev": "3",
    "classtype": "bad-unknown",
    "content": "|01|",
    "depth": "1",
    "offset": "2",
    "metadata": {
      "confidence": "Medium",
      "created_at": "2011_05_31",
      "signature_severity": "Informational",
      "updated_at": "2024_01_30"
    }
  },
  {
    "action": "alert",
    "protocol": "udp",
    "source_ip": "$HOME_NET",
    "source_port": "any",
    "destination_ip": "any",
    "destination_port": "53",
    "sid": "2012903",
    "msg": "ET DNS DNS Query for a Suspicious *.qc.cx domain",
    "rev": "3",
    "classtype": "bad-unknown",
    "content": "|01|",
    "depth": "1",
    "offset": "2",
    "metadata": {
      "confidence": "Medium",
      "created_at": "2011_05_31",
      "signature_severity": "Informational",
      "updated_at": "2024_01_30"
    }
  }
]